vaml/__init__.py
vaml/testing.yaml
vaml/testing123
vaml/vaml.py
vaml-0.1.1.dist-info/entry_points.txt
vaml-0.1.1.dist-info/WHEEL
vaml-0.1.1.dist-info/METADATA
vaml-0.1.1.dist-info/RECORD
