Metadata-Version: 2.1
Name: vaml
Version: 0.1.1
Summary: Azure DevOps Variable Groups as YAML files
Home-page: https://github.com/exodus/vaml/
License: MIT
Author: Miguel A. Alvarado V.
Author-email: alvaradoma@gmail.com
Maintainer: Miguel A. Alvarado V.
Maintainer-email: alvaradoma@gmail.com
Requires-Python: >=3.7,<4.0
Classifier: License :: OSI Approved :: MIT License
Classifier: Programming Language :: Python :: 3
Classifier: Programming Language :: Python :: 3.7
Classifier: Programming Language :: Python :: 3.8
Requires-Dist: argparse (>=1.4.0,<2.0.0)
Requires-Dist: click (>=7.1.1,<8.0.0)
Requires-Dist: pyyaml (>=5.3.1,<6.0.0)
Requires-Dist: requests (>=2.23.0,<3.0.0)
Project-URL: Repository, https://github.com/exodus/vaml/
